{
    "id": 1085874,
    "title": "Children's social care spending",
    "display_status": "Awaiting classification",
    "law_used": "foi",
    "url_title": "childrens_social_care_spending_191",
    "created_at": "2024-02-13T09:32:38.289+00:00",
    "events": [
        {
            "created_at": "2024-02-13T09:32:38.963+00:00",
            "message_id": 1600495,
            "type": "outgoing",
            "content": [
                "Dear Sir/Madam,\nMy name is Emily Craigie and I'm writing from LBC Radio. I hope you're well.\nI am writing with a request under the Freedom of Information Act. Could I ask, for the financial years 2018-19, 22-23 and 23-24:\n1.\tHow much did your local authority spend on providing residential placements to children taken into the council's care? Please provide a breakdown for each year, including a projected spend for the rest of 23-24 if it is available.\n2.\tOf that figure, how much of the figure was spent on private-sector residential placements? Again, please provide a breakdown for each year and include a projected spend for the rest of 23-24 if it is available.\n3.\tHow many children were taken into the council's care for each financial year?\nCould I get this information in an Excel spreadsheet.\nI am happy to discuss further over the phone - my number is 07557187585 - and thanks for your consideration.\nYours Faithfully,\nEmily Craigie"
            ]
        },
        {
            "created_at": "2024-02-16T09:20:23.618+00:00",
            "message_id": 2556864,
            "type": "incoming",
            "content": [
                "Dear Emily Craigie,\nThank you for your request for information relating to Children's social\ncare spending which we received on 13/02/2024.\nThis has been logged as a Freedom of Information Request and will be dealt\nwith under the Freedom of Information Act 2000. The reference number for\nyour request can be found above.\nThe Freedom of Information Act 2000 states that we must respond to you\nwithin 20 working days, by 12/03/2024. Please do not hesitate to contact\nus at the email address below if you have any queries.\nYours sincerely,\nSheffield City Council\nPO Box 1283\nSheffield, S1 1UJ\nEmail: [1][Sheffield City Council request email]\nFrom: Emily Craigie <[FOI #1085874 email]>\nSent: Tuesday, February 13, 2024 9:33 AM\nTo: FOI <[Sheffield City Council request email]>\nSubject: Freedom of Information request - Children's social care spending\nDear Sir/Madam,\nMy name is Emily Craigie and I'm writing from LBC Radio. I hope you're\nwell.\nI am writing with a request under the Freedom of Information Act. Could I\nask, for the financial years 2018-19, 22-23 and 23-24:\n1.\u00a0\u00a0\u00a0\u00a0\u00a0 How much did your local authority spend on providing residential\nplacements to children taken into the council's care? Please provide a\nbreakdown for each year, including a projected spend for the rest of 23-24\nif it is available.\n2.\u00a0\u00a0\u00a0\u00a0\u00a0 Of that figure, how much of the figure was spent on private-sector\nresidential placements? Again, please provide a breakdown for each year\nand include a projected spend for the rest of 23-24 if it is available.\n3.\u00a0\u00a0\u00a0\u00a0\u00a0 How many children were taken into the council's care for each\nfinancial year?\nCould I get this information in an Excel spreadsheet.\nI am happy to discuss further over the phone - my number is 07557187585 -\nand thanks for your consideration.\nYours Faithfully,\nEmily Craigie\n-------------------------------------------------------------------\nPlease use this email address for all replies to this request:\n[2][FOI #1085874 email]\nIs [3][Sheffield City Council request email] the wrong address for Freedom of Information\nrequests to Sheffield City Council? If so, please contact us using this\nform:\n[4]\nhttps://eur03.safelinks.protection.outlo...\nDisclaimer: This message and any reply that you make will be published on\nthe internet. Our privacy and copyright policies:\n[5]\nhttps://eur03.safelinks.protection.outlo...\nFor more detailed guidance on safely disclosing information, read the\nlatest advice from the ICO:\n[6]\nhttps://eur03.safelinks.protection.outlo...\n[7]\nhttps://eur03.safelinks.protection.outlo...\nPlease note that in some cases publication of requests and responses will\nbe delayed.\nIf you find this service useful as an FOI officer, please ask your web\nmanager to link to us from your organisation's FOI page.\nshow quoted sections"
            ]
        },
        {
            "created_at": "2024-02-27T15:13:08.990+00:00",
            "message_id": 2568386,
            "type": "incoming",
            "content": [
                "Dear Emily Craigie,\nThank you for your request for information relating to Children's social\ncare spending which we received on 13/02/2024.\nThis has been logged as a Freedom of Information Request and will be dealt\nwith under the Freedom of Information Act 2000. The reference number for\nyour request can be found above.\nBefore we can begin to process your FOI Request, we would like to clarify\nwhat information you require.\nCould you please clarify the questions asked as they can be interpreted in\ndifferent ways which would give very different answers.\nSuch as: The costs of all internal / external placements in that year\n(including new and existing placements) or the costs in those financial\nyears purely for placements starting in those years?\nThe Freedom of Information Act 2000 states that we must respond to a\nrequest within 20 working days. The 20 working day clock will start the\nday after we receive the necessary clarification.\nYou can provide your clarification by replying to this email. Please\nnote, if clarification is not received within 2 months your Freedom of\nInformation request will be closed.\nWe look forward to hearing from you.\nYours sincerely,\nSheffield City Council\nPO Box 1283\nSheffield, S1 1UJ\nEmail: [1][Sheffield City Council request email]\nFrom: Emily Craigie <[2][FOI #1085874 email]>\nSent: Tuesday, February 13, 2024 9:33 AM\nTo: FOI <[3][Sheffield City Council request email]>\nSubject: Freedom of Information request - Children's social care spending\nDear Sir/Madam,\nMy name is Emily Craigie and I'm writing from LBC Radio. I hope you're\nwell.\nI am writing with a request under the Freedom of Information Act. Could I\nask, for the financial years 2018-19, 22-23 and 23-24:\n1. How much did your local authority spend on providing residential\nplacements to children taken into the council's care? Please provide a\nbreakdown for each year, including a projected spend for the rest of 23-24\nif it is available.\n2. Of that figure, how much of the figure was spent on private-sector\nresidential placements? Again, please provide a breakdown for each year\nand include a projected spend for the rest of 23-24 if it is available.\n3. How many children were taken into the council's care for each financial\nyear?\nCould I get this information in an Excel spreadsheet.\nI am happy to discuss further over the phone - my number is 07557187585 -\nand thanks for your consideration.\nYours Faithfully,\nEmily Craigie\n-------------------------------------------------------------------\nPlease use this email address for all replies to this request:\n[4][FOI #1085874 email]\nIs [5][Sheffield City Council request email] the wrong address for Freedom of Information\nrequests to Sheffield City Council? If so, please contact us using this\nform:\n[6]\nhttps://eur03.safelinks.protection.outlo...\nDisclaimer: This message and any reply that you make will be published on\nthe internet. Our privacy and copyright policies:\n[7]\nhttps://eur03.safelinks.protection.outlo...\nFor more detailed guidance on safely disclosing information, read the\nlatest advice from the ICO:\n[8]\nhttps://eur03.safelinks.protection.outlo...\n[9]\nhttps://eur03.safelinks.protection.outlo...\nPlease note that in some cases publication of requests and responses will\nbe delayed.\nIf you find this service useful as an FOI officer, please ask your web\nmanager to link to us from your organisation's FOI page.\nshow quoted sections"
            ]
        }
    ]
}