{
    "id": 1275354,
    "title": "Dog fouling fines and reports statistics (2019-2024)",
    "display_status": "Awaiting response",
    "law_used": "foi",
    "url_title": "dog_fouling_fines_and_reports_st_7",
    "created_at": "2025-04-25T05:31:59.603+01:00",
    "events": [
        {
            "created_at": "2025-04-25T05:31:59.959+01:00",
            "message_id": 1851629,
            "type": "outgoing",
            "content": [
                "Dear Sheffield City Council,\nI am writing to request information under the Freedom of Information Act 2000 regarding dog fouling in your area.\nSpecific Data Requirements (2019-2024):\n1. Dog ownership demographics\n- Annual total dog ownership numbers\n2. Dog Population Metrics\n- Annual total registered dog population\n- Breed category distribution\n3. Dog Fouling Fines\n- Annual average dog fouling fine (\u00a3)\n- Annual total dog fouling fines issued (\u00a3)\n- Annual total dog fouling fines successfully collected (\u00a3)\n4. Dog Fouling Incident Report\n- Annual total dog fouling complaints/reports\n- Incident location categorization\nData Format Preferences:\n- Excel (.xlsx) or CSV file format\n- Yearly columnar presentation for ownership rate, dog population, fine amounts and complaint numbers\nIn instances where specific data points are unavailable, kindly provide the most relevant information possible for our study.\nPlease let me know if you require further clarification about our data requirements. We would appreciate your assistance in compiling this information.\nThank you for your help."
            ]
        },
        {
            "created_at": "2025-04-28T12:38:07.398+01:00",
            "message_id": 3000582,
            "type": "incoming",
            "content": [
                "Dear Daryll Dulay,\nThank you for your request for information relating to dog fouling fines\nand reports statistics (2019-2024) which we received on 24/04/2025.\nAs your request is a request for information relating to the environment,\nthis has been logged as a request under the Environmental Information\nRegulations 2004 (EIR) and will be dealt with under the Regulations. The\nreference number for your request can be found above.\nThe Environmental Information Regulations 2004 state that we must respond\nto you within 20 working days, by 23/05/2025. Please do not hesitate to\ncontact us at the email address below if you have any queries.\nPlease note that from 1^st January 2025, as part of our commitment to\nimproving services, the council will accept EIR requests via the online\nform which can be found here:\n[1]Freedom of Information and Environmental Information requests |\nSheffield City Council\nPlease bookmark this link for future requests.\nThe online form is linked directly to our systems in the FOI service as\npart of our continued improvement to streamline processes.\nYours sincerely,\nSheffield City Council\nPO Box 1283\nSheffield, S1 1UJ\nEmail: [2][Sheffield City Council request email]\nThis Email, and any attachments, may contain non-public information and is\nintended solely for the individual(s) to whom it is addressed. It may\ncontain sensitive or protectively marked material and should be handled\naccordingly. If this Email has been misdirected, please notify the author\nimmediately. If you are not the intended recipient you must not disclose,\ndistribute, copy, print or rely on any of the information contained in it\nor attached, and all copies must be deleted immediately. Whilst we take\nreasonable steps to try to identify any software viruses, any attachments\nto this Email may nevertheless contain viruses which our anti-virus\nsoftware has failed to identify. You should therefore carry out your own\nanti-virus checks before opening any documents. Sheffield City Council\nwill not accept any liability for damage caused by computer viruses\nemanating from any attachment or other document supplied with this e-mail\nReferences\nVisible links\n1.\nhttps://www.sheffield.gov.uk/your-city-c...\n2. mailto:[sheffield%20city%20council%20request%20email]"
            ]
        }
    ]
}