{
    "id": 989410,
    "title": "I am writing to kindly request information regarding the budget allocation for taxi/private hire licensing",
    "display_status": "Successful",
    "law_used": "foi",
    "url_title": "i_am_writing_to_kindly_request_i",
    "created_at": "2023-06-10T23:54:01.567+01:00",
    "events": [
        {
            "created_at": "2023-06-10T23:54:01.788+01:00",
            "message_id": 1473207,
            "type": "outgoing",
            "content": [
                "Dear Sheffield City Council,\nI am writing to kindly request information regarding the budget allocation for taxi/private hire licensing over the past three years. Specifically, I would like to ascertain the total budget for each year and determine whether the funding was entirely derived from licensing fees. Additionally, I am interested in knowing the amount of funds allocated in excess of licensing fees, if any.\nTo assist you in providing the requested information, I have outlined below the specific details I am seeking:\n1. Total Taxi/Private Hire Licensing Budget:\nFinancial Year 1: [Year] - [Amount]\nFinancial Year 2: [Year] - [Amount]\nFinancial Year 3: [Year] - [Amount]\n2. Funding Sources:\nWere the licensing fees the sole source of funding for the taxi/private hire licensing budget in each of the aforementioned years? If not, please specify the additional funding sources.\n3. Excess Funding:\nIf the budget exceeded the revenue generated from licensing fees, kindly provide the amount of funds added in excess of the licensing fees in each year.\nI understand that you may require some time to gather the requested information. However, I kindly request that you provide the data within 20 working days from the date of this request. If there are any concerns or obstacles that may hinder the retrieval of this information, I would greatly appreciate your assistance and guidance in overcoming them.\n4. Recovery of Excess Funds:\nIn the event that funds were allocated in excess of the licensing fees in any of the specified years, I kindly request information on whether these excess funds were recovered or carried over to the subsequent year's budget. If there was a recovery process, please provide details on how it was executed.\nPlease feel free to reach out to me here if you require any further clarification or if there are any specific procedures I need to follow to obtain this information. I sincerely thank you in advance for your attention to this matter and your cooperation.\nYours faithfully,\nMR Kenny"
            ]
        },
        {
            "created_at": "2023-06-13T15:48:36.138+01:00",
            "message_id": 2334991,
            "type": "incoming",
            "content": [
                "Dear Mr Kenny,\nThank you for your request for information relating to Taxi/private hire\nlicensing which we received on 10/06/2023.\nThis has been logged as a Freedom of Information Request and will be dealt\nwith under the Freedom of Information Act 2000. The reference number for\nyour request can be found above.\nThe Freedom of Information Act 2000 states that we must respond to you\nwithin 20 working days, by 07/07/2023. Please do not hesitate to contact\nus at the email address below if you have any queries.\nYours sincerely,\nSheffield City Council\nPO Box 1283\nSheffield, S1 1UJ\nEmail: [1][Sheffield City Council request email]\nFrom: MR Kenny <[FOI #989410 email]>\nSent: Saturday, June 10, 2023 11:54 PM\nTo: FOI <[Sheffield City Council request email]>\nSubject: Freedom of Information request - I am writing to kindly request\ninformation regarding the budget allocation for taxi/private hire\nlicensing\nDear Sheffield City Council,\nI am writing to kindly request information regarding the budget allocation\nfor taxi/private hire licensing over the past three years. Specifically, I\nwould like to ascertain the total budget for each year and determine\nwhether the funding was entirely derived from licensing fees.\nAdditionally, I am interested in knowing the amount of funds allocated in\nexcess of licensing fees, if any.\nTo assist you in providing the requested information, I have outlined\nbelow the specific details I am seeking:\n1. Total Taxi/Private Hire Licensing Budget:\nFinancial Year 1: [Year] - [Amount]\nFinancial Year 2: [Year] - [Amount]\nFinancial Year 3: [Year] - [Amount]\n2. Funding Sources:\nWere the licensing fees the sole source of funding for the taxi/private\nhire licensing budget in each of the aforementioned years? If not, please\nspecify the additional funding sources.\n3. Excess Funding:\nIf the budget exceeded the revenue generated from licensing fees, kindly\nprovide the amount of funds added in excess of the licensing fees in each\nyear.\nI understand that you may require some time to gather the requested\ninformation. However, I kindly request that you provide the data within 20\nworking days from the date of this request. If there are any concerns or\nobstacles that may hinder the retrieval of this information, I would\ngreatly appreciate your assistance and guidance in overcoming them.\n4. Recovery of Excess Funds:\nIn the event that funds were allocated in excess of the licensing fees in\nany of the specified years, I kindly request information on whether these\nexcess funds were recovered or carried over to the subsequent year's\nbudget. If there was a recovery process, please provide details on how it\nwas executed.\nPlease feel free to reach out to me here if you require any further\nclarification or if there are any specific procedures I need to follow to\nobtain this information. I sincerely thank you in advance for your\nattention to this matter and your cooperation.\nYours faithfully,\nMR Kenny\n-------------------------------------------------------------------\nPlease use this email address for all replies to this request:\n[2][FOI #989410 email]\nIs [3][Sheffield City Council request email] the wrong address for Freedom of Information\nrequests to Sheffield City Council? If so, please contact us using this\nform:\n[4]\nhttps://eur03.safelinks.protection.outlo...\nDisclaimer: This message and any reply that you make will be published on\nthe internet. Our privacy and copyright policies:\n[5]\nhttps://eur03.safelinks.protection.outlo...\nFor more detailed guidance on safely disclosing information, read the\nlatest advice from the ICO:\n[6]\nhttps://eur03.safelinks.protection.outlo...\n[7]\nhttps://eur03.safelinks.protection.outlo...\nPlease note that in some cases publication of requests and responses will\nbe delayed.\nIf you find this service useful as an FOI officer, please ask your web\nmanager to link to us from your organisation's FOI page.\nshow quoted sections"
            ]
        },
        {
            "created_at": "2023-07-07T18:08:06.940+01:00",
            "message_id": 2357444,
            "type": "incoming",
            "content": [
                "1 Attachment\nFOI 875955 Taxi Licensing 14.06.23.xlsx\n18K\nDownload\nView as HTML\nDear Mr Kenny,\nThank you for your request for information relating to Taxi/private hire\nlicensing which we received on 10/06/2023.\nPlease find Sheffield City Council\u2019s response to your request set out\nbelow:\nPlease see the attached document.\nPlease note, that in 20/21 we did not record taxi/private licensing as a\nbudget separate from all other licensing activity.\nIf you have any queries about this response, please do not hesitate to\ncontact us.\nThe information provided in this response is available for re-use under\nthe terms of the Open Government Licence v3.0. The terms of the OGL can be\nfound [1]here. When re-using the information, Sheffield City Council\nrequires you to include the following attribution statement: \u201cContains\npublic sector information obtained from Sheffield City Council and\nlicensed under the Open Government Licence v3.0.\u201d\nIf you are unhappy with the response you have received in relation to your\nrequest, you are entitled to have this reviewed. You can ask for an\ninternal review by replying to this email. Internal review requests should\nbe submitted within 40 working days from the date of this response.\nIf you remain dissatisfied with the outcome of your internal review, you\ncan contact the Information Commissioner\u2019s Office. Please see\n[2]\nhttps://ico.org.uk/make-a-complaint/offi...\nfor further details.\nKind Regards,\nSheffield City Council\nPO Box 1283\nSheffield, S1 1UJ\nEmail: [3][Sheffield City Council request email]\nFrom: Michelle Lint (NCC) On Behalf Of FOI\nSent: Tuesday, June 13, 2023 3:48 PM\nTo: 'MR Kenny' <[FOI #989410 email]>\nSubject: Re \u2013 Freedom of Information Request \u2013 Reference \u2013 FOI /875955\nDear Mr Kenny,\nThank you for your request for information relating to Taxi/private hire\nlicensing which we received on 10/06/2023.\nThis has been logged as a Freedom of Information Request and will be dealt\nwith under the Freedom of Information Act 2000. The reference number for\nyour request can be found above.\nThe Freedom of Information Act 2000 states that we must respond to you\nwithin 20 working days, by 07/07/2023. Please do not hesitate to contact\nus at the email address below if you have any queries.\nYours sincerely,\nSheffield City Council\nPO Box 1283\nSheffield, S1 1UJ\nEmail: [4][Sheffield City Council request email]\nFrom: MR Kenny <[5][FOI #989410 email]>\nSent: Saturday, June 10, 2023 11:54 PM\nTo: FOI <[6][Sheffield City Council request email]>\nSubject: Freedom of Information request - I am writing to kindly request\ninformation regarding the budget allocation for taxi/private hire\nlicensing\nDear Sheffield City Council,\nI am writing to kindly request information regarding the budget allocation\nfor taxi/private hire licensing over the past three years. Specifically, I\nwould like to ascertain the total budget for each year and determine\nwhether the funding was entirely derived from licensing fees.\nAdditionally, I am interested in knowing the amount of funds allocated in\nexcess of licensing fees, if any.\nTo assist you in providing the requested information, I have outlined\nbelow the specific details I am seeking:\n1. Total Taxi/Private Hire Licensing Budget:\nFinancial Year 1: [Year] - [Amount]\nFinancial Year 2: [Year] - [Amount]\nFinancial Year 3: [Year] - [Amount]\n2. Funding Sources:\nWere the licensing fees the sole source of funding for the taxi/private\nhire licensing budget in each of the aforementioned years? If not, please\nspecify the additional funding sources.\n3. Excess Funding:\nIf the budget exceeded the revenue generated from licensing fees, kindly\nprovide the amount of funds added in excess of the licensing fees in each\nyear.\nI understand that you may require some time to gather the requested\ninformation. However, I kindly request that you provide the data within 20\nworking days from the date of this request. If there are any concerns or\nobstacles that may hinder the retrieval of this information, I would\ngreatly appreciate your assistance and guidance in overcoming them.\n4. Recovery of Excess Funds:\nIn the event that funds were allocated in excess of the licensing fees in\nany of the specified years, I kindly request information on whether these\nexcess funds were recovered or carried over to the subsequent year's\nbudget. If there was a recovery process, please provide details on how it\nwas executed.\nPlease feel free to reach out to me here if you require any further\nclarification or if there are any specific procedures I need to follow to\nobtain this information. I sincerely thank you in advance for your\nattention to this matter and your cooperation.\nYours faithfully,\nMR Kenny\n-------------------------------------------------------------------\nPlease use this email address for all replies to this request:\n[7][FOI #989410 email]\nIs [8][Sheffield City Council request email] the wrong address for Freedom of Information\nrequests to Sheffield City Council? If so, please contact us using this\nform:\n[9]\nhttps://eur03.safelinks.protection.outlo...\nDisclaimer: This message and any reply that you make will be published on\nthe internet. Our privacy and copyright policies:\n[10]\nhttps://eur03.safelinks.protection.outlo...\nFor more detailed guidance on safely disclosing information, read the\nlatest advice from the ICO:\n[11]\nhttps://eur03.safelinks.protection.outlo...\n[12]\nhttps://eur03.safelinks.protection.outlo...\nPlease note that in some cases publication of requests and responses will\nbe delayed.\nIf you find this service useful as an FOI officer, please ask your web\nmanager to link to us from your organisation's FOI page.\nshow quoted sections"
            ]
        }
    ]
}